{"v":"5.7.1","fr":30.0000305175781,"ip":0,"op":91.000092569987,"w":500,"h":500,"nm":"tiktok","ddd":0,"assets":[{"id":"comp_0","layers":[{"ddd":0,"ind":1,"ty":4,"nm":"logo","sr":1,"ks":{"o":{"a":0,"k":100,"ix":11},"r":{"a":0,"k":0,"ix":10},"p":{"a":1,"k":[{"i":{"x":0.833,"y":0.833},"o":{"x":0.167,"y":0.167},"t":0,"s":[242.693,241.314,0],"to":[-7.986,-9.899,0],"ti":[0,10.162,0]},{"i":{"x":0.833,"y":0.833},"o":{"x":0.167,"y":0.167},"t":13.006,"s":[226.937,209.969,0],"to":[0,-12.54,0],"ti":[-12.538,0,0]},{"i":{"x":0.833,"y":0.833},"o":{"x":0.167,"y":0.167},"t":26.021,"s":[249.679,187.222,0],"to":[12.542,0,0],"ti":[0,-12.54,0]},{"i":{"x":0.833,"y":0.833},"o":{"x":0.167,"y":0.167},"t":39.078,"s":[272.598,209.969,0],"to":[0,15.231,0],"ti":[0,0,0]},{"i":{"x":0.833,"y":0.833},"o":{"x":0.167,"y":0.167},"t":57.124,"s":[247.789,251.963,0],"to":[-10.459,12.409,0],"ti":[0,-11.801,0]},{"i":{"x":0.833,"y":0.833},"o":{"x":0.167,"y":0.167},"t":72.978,"s":[226.937,289.26,0],"to":[0,12.542,0],"ti":[-12.54,0,0]},{"i":{"x":0.833,"y":0.833},"o":{"x":0.167,"y":0.167},"t":86.033,"s":[249.855,312,0],"to":[12.535,0,0],"ti":[0,12.542,0]},{"i":{"x":0.833,"y":0.833},"o":{"x":0.167,"y":0.167},"t":99.046,"s":[272.598,289.26,0],"to":[0,-10.162,0],"ti":[7.991,9.891,0]},{"i":{"x":0.833,"y":0.833},"o":{"x":0.167,"y":0.167},"t":112.055,"s":[256.839,257.911,0],"to":[0,0,0],"ti":[0,0,0]},{"t":120.000122070313,"s":[242.693,241.314,0]}],"ix":2,"x":"var $bm_rt;\n$bm_rt = loopOut('cycle');"},"a":{"a":0,"k":[0,0,0],"ix":1},"s":{"a":0,"k":[44,44,100],"ix":6}},"ao":0,"shapes":[{"ty":"gr","it":[{"ind":0,"ty":"sh","ix":1,"ks":{"a":0,"k":{"i":[[0,0],[0,0],[-194.248,-11.545],[0,-143.018],[70.486,62.867],[0,0],[131.388,-24.918],[55.641,12.155],[-321.847,-50.876],[0,-153.524],[-35.33,-79.198],[-46.177,101.72],[0,25.485],[0,0]],"o":[[0,0],[0.042,12.803],[0,172.2],[-14.594,0.865],[0,0],[1.743,126.073],[-36.812,6.971],[-320.534,-95.882],[0,153.481],[-132.957,-19.561],[32.155,72.1],[5.228,-19.908],[0,0],[0,0]],"v":[[160.651,-420.534],[160.651,-419.827],[358.689,-210.378],[358.777,-67.36],[160.432,-137.546],[160.214,140.874],[-39.611,415.497],[-165.21,411.097],[-57.385,-109.317],[-57.297,44.164],[-199.402,214.408],[11.314,200.425],[19.157,132.335],[19.157,-420.534]],"c":true},"ix":2},"nm":"Path 1","mn":"ADBE Vector Shape - Group","hd":false},{"ty":"fl","c":{"a":0,"k":[0,0,0,1],"ix":4},"o":{"a":0,"k":100,"ix":5},"r":1,"bm":0,"nm":"Fill 1","mn":"ADBE Vector Graphic - Fill","hd":false},{"ty":"tr","p":{"a":0,"k":[0,0],"ix":2},"a":{"a":0,"k":[0,0],"ix":1},"s":{"a":0,"k":[100,100],"ix":3},"r":{"a":0,"k":0,"ix":6},"o":{"a":0,"k":100,"ix":7},"sk":{"a":0,"k":0,"ix":4},"sa":{"a":0,"k":0,"ix":5},"nm":"Transform"}],"nm":"Group 1","np":2,"cix":2,"bm":0,"ix":1,"mn":"ADBE Vector Group","hd":false}],"ip":0,"op":241.000245157878,"st":0,"bm":0},{"ddd":0,"ind":2,"ty":4,"nm":"logo blue","sr":1,"ks":{"o":{"a":0,"k":100,"ix":11},"r":{"a":0,"k":0,"ix":10},"p":{"a":1,"k":[{"i":{"x":0.833,"y":0.833},"o":{"x":0.167,"y":0.167},"t":-6,"s":[242.693,241.314,0],"to":[-7.986,-9.899,0],"ti":[0,10.162,0]},{"i":{"x":0.833,"y":0.833},"o":{"x":0.167,"y":0.167},"t":7.006,"s":[226.937,209.969,0],"to":[0,-12.54,0],"ti":[-12.538,0,0]},{"i":{"x":0.833,"y":0.833},"o":{"x":0.167,"y":0.167},"t":20.021,"s":[249.679,187.222,0],"to":[12.542,0,0],"ti":[0,-12.54,0]},{"i":{"x":0.833,"y":0.833},"o":{"x":0.167,"y":0.167},"t":33.078,"s":[272.598,209.969,0],"to":[0,15.231,0],"ti":[0,0,0]},{"i":{"x":0.833,"y":0.833},"o":{"x":0.167,"y":0.167},"t":51.124,"s":[247.789,251.963,0],"to":[-10.459,12.409,0],"ti":[0,-11.801,0]},{"i":{"x":0.833,"y":0.833},"o":{"x":0.167,"y":0.167},"t":66.978,"s":[226.937,289.26,0],"to":[0,12.542,0],"ti":[-12.54,0,0]},{"i":{"x":0.833,"y":0.833},"o":{"x":0.167,"y":0.167},"t":80.033,"s":[249.855,312,0],"to":[12.535,0,0],"ti":[0,12.542,0]},{"i":{"x":0.833,"y":0.833},"o":{"x":0.167,"y":0.167},"t":93.046,"s":[272.598,289.26,0],"to":[0,-10.162,0],"ti":[7.991,9.891,0]},{"i":{"x":0.833,"y":0.833},"o":{"x":0.167,"y":0.167},"t":106.055,"s":[256.839,257.911,0],"to":[0,0,0],"ti":[0,0,0]},{"t":114.000115966797,"s":[242.693,241.314,0]}],"ix":2,"x":"var $bm_rt;\n$bm_rt = loopOut('cycle');"},"a":{"a":0,"k":[0,0,0],"ix":1},"s":{"a":0,"k":[44,44,100],"ix":6}},"ao":0,"shapes":[{"ty":"gr","it":[{"ind":0,"ty":"sh","ix":1,"ks":{"a":0,"k":{"i":[[0,0],[0,0],[-194.248,-11.545],[0,-143.018],[70.486,62.867],[0,0],[131.388,-24.918],[55.641,12.155],[-321.847,-50.876],[0,-153.524],[-35.33,-79.198],[-46.177,101.72],[0,25.485],[0,0]],"o":[[0,0],[0.042,12.803],[0,172.2],[-14.594,0.865],[0,0],[1.743,126.073],[-36.812,6.971],[-320.534,-95.882],[0,153.481],[-132.957,-19.561],[32.155,72.1],[5.228,-19.908],[0,0],[0,0]],"v":[[160.651,-420.534],[160.651,-419.827],[358.689,-210.378],[358.777,-67.36],[160.432,-137.546],[160.214,140.874],[-39.611,415.497],[-165.21,411.097],[-57.385,-109.317],[-57.297,44.164],[-199.402,214.408],[11.314,200.425],[19.157,132.335],[19.157,-420.534]],"c":true},"ix":2},"nm":"Path 1","mn":"ADBE Vector Shape - Group","hd":false},{"ty":"fl","c":{"a":0,"k":[0,0.968627510819,0.937254961799,1],"ix":4},"o":{"a":0,"k":100,"ix":5},"r":1,"bm":0,"nm":"Fill 1","mn":"ADBE Vector Graphic - Fill","hd":false},{"ty":"tr","p":{"a":0,"k":[0,0],"ix":2},"a":{"a":0,"k":[0,0],"ix":1},"s":{"a":0,"k":[100,100],"ix":3},"r":{"a":0,"k":0,"ix":6},"o":{"a":0,"k":100,"ix":7},"sk":{"a":0,"k":0,"ix":4},"sa":{"a":0,"k":0,"ix":5},"nm":"Transform"}],"nm":"Group 1","np":2,"cix":2,"bm":0,"ix":1,"mn":"ADBE Vector Group","hd":false}],"ip":-6.00000610351563,"op":241.000245157878,"st":-6.00000610351563,"bm":0},{"ddd":0,"ind":3,"ty":4,"nm":"logo red","sr":1,"ks":{"o":{"a":0,"k":100,"ix":11},"r":{"a":0,"k":0,"ix":10},"p":{"a":1,"k":[{"i":{"x":0.833,"y":0.833},"o":{"x":0.167,"y":0.167},"t":-114,"s":[242.693,241.314,0],"to":[-7.986,-9.899,0],"ti":[0,10.162,0]},{"i":{"x":0.833,"y":0.833},"o":{"x":0.167,"y":0.167},"t":-100.994,"s":[226.937,209.969,0],"to":[0,-12.54,0],"ti":[-12.538,0,0]},{"i":{"x":0.833,"y":0.833},"o":{"x":0.167,"y":0.167},"t":-87.98,"s":[249.679,187.222,0],"to":[12.542,0,0],"ti":[0,-12.54,0]},{"i":{"x":0.833,"y":0.833},"o":{"x":0.167,"y":0.167},"t":-74.922,"s":[272.598,209.969,0],"to":[0,15.231,0],"ti":[0,0,0]},{"i":{"x":0.833,"y":0.833},"o":{"x":0.167,"y":0.167},"t":-56.876,"s":[247.789,251.963,0],"to":[-10.459,12.409,0],"ti":[0,-11.801,0]},{"i":{"x":0.833,"y":0.833},"o":{"x":0.167,"y":0.167},"t":-41.023,"s":[226.937,289.26,0],"to":[0,12.542,0],"ti":[-12.54,0,0]},{"i":{"x":0.833,"y":0.833},"o":{"x":0.167,"y":0.167},"t":-27.967,"s":[249.855,312,0],"to":[12.535,0,0],"ti":[0,12.542,0]},{"i":{"x":0.833,"y":0.833},"o":{"x":0.167,"y":0.167},"t":-14.954,"s":[272.598,289.26,0],"to":[0,-10.162,0],"ti":[7.991,9.891,0]},{"i":{"x":0.833,"y":0.833},"o":{"x":0.167,"y":0.167},"t":-1.945,"s":[256.839,257.911,0],"to":[0,0,0],"ti":[0,0,0]},{"t":6.00000610351563,"s":[242.693,241.314,0]}],"ix":2,"x":"var $bm_rt;\n$bm_rt = loopOut('cycle');"},"a":{"a":0,"k":[0,0,0],"ix":1},"s":{"a":0,"k":[44,44,100],"ix":6}},"ao":0,"shapes":[{"ty":"gr","it":[{"ind":0,"ty":"sh","ix":1,"ks":{"a":0,"k":{"i":[[0,0],[0,0],[-194.248,-11.545],[0,-143.018],[70.486,62.867],[0,0],[131.388,-24.918],[55.641,12.155],[-321.847,-50.876],[0,-153.524],[-35.33,-79.198],[-46.177,101.72],[0,25.485],[0,0]],"o":[[0,0],[0.042,12.803],[0,172.2],[-14.594,0.865],[0,0],[1.743,126.073],[-36.812,6.971],[-320.534,-95.882],[0,153.481],[-132.957,-19.561],[32.155,72.1],[5.228,-19.908],[0,0],[0,0]],"v":[[160.651,-420.534],[160.651,-419.827],[358.689,-210.378],[358.777,-67.36],[160.432,-137.546],[160.214,140.874],[-39.611,415.497],[-165.21,411.097],[-57.385,-109.317],[-57.297,44.164],[-199.402,214.408],[11.314,200.425],[19.157,132.335],[19.157,-420.534]],"c":true},"ix":2},"nm":"Path 1","mn":"ADBE Vector Shape - Group","hd":false},{"ty":"fl","c":{"a":0,"k":[1,0,0.309803921569,1],"ix":4},"o":{"a":0,"k":100,"ix":5},"r":1,"bm":0,"nm":"Fill 1","mn":"ADBE Vector Graphic - Fill","hd":false},{"ty":"tr","p":{"a":0,"k":[0,0],"ix":2},"a":{"a":0,"k":[0,0],"ix":1},"s":{"a":0,"k":[100,100],"ix":3},"r":{"a":0,"k":0,"ix":6},"o":{"a":0,"k":100,"ix":7},"sk":{"a":0,"k":0,"ix":4},"sa":{"a":0,"k":0,"ix":5},"nm":"Transform"}],"nm":"Group 1","np":2,"cix":2,"bm":0,"ix":1,"mn":"ADBE Vector Group","hd":false}],"ip":-114.000115966797,"op":241.000245157878,"st":-114.000115966797,"bm":0}]}],"layers":[{"ddd":0,"ind":1,"ty":0,"nm":"Comp 1","refId":"comp_0","sr":1,"ks":{"o":{"a":0,"k":100,"ix":11},"r":{"a":0,"k":0,"ix":10},"p":{"a":0,"k":[250,250,0],"ix":2},"a":{"a":0,"k":[250,250,0],"ix":1},"s":{"a":0,"k":[88,88,100],"ix":6}},"ao":0,"tm":{"a":1,"k":[{"i":{"x":[0.833],"y":[0.833]},"o":{"x":[0.167],"y":[0.167]},"t":0,"s":[0]},{"t":91.000092569987,"s":[8.033]}],"ix":2},"w":500,"h":500,"ip":0,"op":91.000092569987,"st":0,"bm":0}],"markers":[]}